__paths__.py
notebooks/__init__.py
notebooks/co_occurrence/__init__.py
notebooks/co_occurrence/co_occurrence_trends.ipynb
notebooks/co_occurrence/co_occurrence_trends.py
notebooks/most_discriminating_words/__init__.py
notebooks/most_discriminating_words/most_discriminating_terms.ipynb
notebooks/most_discriminating_words/most_discriminating_terms.py
notebooks/pos_statistics/__init__.py
notebooks/pos_statistics/pos_statistics.ipynb
notebooks/pos_statistics/pos_statistics.py
notebooks/source/__init__.py
notebooks/source/courier.py
notebooks/topic_modelling/explore_topic_models.ipynb
notebooks/topic_modelling/explore_topic_models.py
notebooks/word_trends/__init__.py
notebooks/word_trends/word_trends.ipynb
notebooks/word_trends/word_trends.py
humlab_inidun-0.3.18.dist-info/METADATA
humlab_inidun-0.3.18.dist-info/WHEEL
humlab_inidun-0.3.18.dist-info/RECORD
